LICENSE
MANIFEST.in
README.rst
setup.py
VESPA.egg-info/PKG-INFO
VESPA.egg-info/SOURCES.txt
VESPA.egg-info/dependency_links.txt
VESPA.egg-info/not-zip-safe
VESPA.egg-info/requires.txt
VESPA.egg-info/top_level.txt
scripts/batch_koifpp_condor
scripts/calcfpp
scripts/get_kepler_ttvs
scripts/get_trilegal
scripts/koifpp
scripts/koifpp-config
vespa/__init__.py
vespa/_transitutils.c
vespa/_transitutils.pyx
vespa/fitebs.py
vespa/fpp.py
vespa/hashutils.py
vespa/kde.py
vespa/kepler.py
vespa/plotutils.py
vespa/populations.py
vespa/statutils.py
vespa/transit_basic.py
vespa/transitsignal.py
vespa/data/kep22field.h5
vespa/data/kepler_chiplocs.txt
vespa/data/keplerld.dat
vespa/orbits/__init__.py
vespa/orbits/kepler.py
vespa/orbits/populations.py
vespa/orbits/utils.py
vespa/orbits/data/Etable.npy
vespa/orbits/data/Etable_Ms.npy
vespa/orbits/data/Etable_eccs.npy
vespa/stars/__init__.py
vespa/stars/association.py
vespa/stars/constraints.py
vespa/stars/contrastcurve.py
vespa/stars/extinction.py
vespa/stars/populations.py
vespa/stars/trilegal.py
vespa/stars/utils.py
vespa/stars/data/extinction.txt
vespa/stars/data/multiple_pecc.txt
vespa/stars/data/raghavan_periods.dat
vespa/stars/tests/__init__.py
vespa/stars/tests/test_populations.py
vespa/tests/__init__.py
vespa/tests/fpp.ini
vespa/tests/star.ini
vespa/tests/test.ini
vespa/tests/test_fpp.py
vespa/tests/test_populations.py
vespa/tests/test_transit.py
vespa/tests/trsig.pkl
vespa/tests/kepler-22/fpp.ini
vespa/tests/kepler-22/fpp_cadence.ini
vespa/tests/kepler-22/fpp_cc.ini
vespa/tests/kepler-22/fpp_cc2.ini
vespa/tests/kepler-22/keck_K.cc
vespa/tests/kepler-22/mist_starmodel_binary.h5
vespa/tests/kepler-22/mist_starmodel_single.h5
vespa/tests/kepler-22/mist_starmodel_triple.h5
vespa/tests/kepler-22/popset.h5
vespa/tests/kepler-22/roboao_i.cc
vespa/tests/kepler-22/signal.txt
vespa/tests/kepler-22/star.ini
vespa/tests/kepler-22/starfield.h5
vespa/tests/kepler-22/trsig.pkl