Metadata-Version: 1.1
Name: VESPA
Version: 0.6
Summary: Calculate astrophysical false positive probabilities for transiting exoplanet signals
Home-page: https://github.com/timothydmorton/VESPA
Author: Timothy D. Morton
Author-email: tim.morton@gmail.com
License: UNKNOWN
Platform: UNKNOWN
Classifier: Development Status :: 4 - Beta
Classifier: Intended Audience :: Science/Research
Classifier: Operating System :: OS Independent
Classifier: Programming Language :: Python
Classifier: Topic :: Scientific/Engineering
Classifier: Topic :: Scientific/Engineering :: Astronomy
